[
  {
    "upvotes": 0,
    "_id": "5bcf30f5e7179a4377014e44",
    "AlbumName": "Taboo",
    "Artist": "Denzel Curry"
  },
  {
    "upvotes": 0,
    "_id": "5bd04c38e7179a176d3afaaf",
    "AlbumName": "Powder",
    "Artist": "Bones"
  },
  {
    "upvotes": 0,
    "_id": "5bd04c6d9be9f40696e685d1",
    "AlbumName": "iwtdino",
    "Artist": "SB",
    "__v": 0
  },
  {
    "upvotes": 0,
    "_id": "5bd04f7da8346f072b3ff6f7",
    "AlbumName": "test",
    "Artist": "SB",
    "__v": 0
  },
  {
    "upvotes": 0,
    "_id": "5bd0505ae44731075074af07",
    "AlbumName": "test1",
    "Artist": "SB",
    "__v": 0
  },
  {
    "upvotes": 0,
    "_id": "5bd050a24dde9807602e0cd7",
    "AlbumName": "test2",
    "Artist": "SB",
    "__v": 0
  }
]